rgbmaker/__init__.py
rgbmaker/cli.py
rgbmaker/fetch.py
rgbmaker/imgplt.py
rgbmaker/tgss_spidx.py
rgbmaker/wrightCC.py
rgbmaker-0.0.5.10.dist-info/licenses/LICENSE.rst
rgbmaker-0.0.5.10.dist-info/METADATA
rgbmaker-0.0.5.10.dist-info/WHEEL
rgbmaker-0.0.5.10.dist-info/entry_points.txt
rgbmaker-0.0.5.10.dist-info/top_level.txt
rgbmaker-0.0.5.10.dist-info/RECORD
