Metadata-Version: 2.4
Name: rgbmaker
Version: 0.0.5.10
Summary: A python package which communicates to different astronomical services and fetches fits and numerical data.
Home-page: https://github.com/avialxee/rgbmaker
Author: Avinash Kumar
Author-email: avialxee@gmail.com
Project-URL: Bug Tracker, https://github.com/avialxee/rgbmaker/issues
Classifier: Programming Language :: Python :: 3
Classifier: Programming Language :: Python :: 3.7
Classifier: Programming Language :: Python :: 3.8
Classifier: Programming Language :: Python :: 3.9
Classifier: Programming Language :: Python :: 3.10
Classifier: License :: OSI Approved :: BSD License
Classifier: Intended Audience :: Science/Research
License-File: LICENSE.rst
Requires-Dist: astropy>=4.2.1
Requires-Dist: matplotlib<=3.5.3,>=3.4.2
Requires-Dist: regions
Requires-Dist: numpy>=1.20.3
Requires-Dist: astroquery
Requires-Dist: requests
Requires-Dist: scipy
Provides-Extra: dev
Requires-Dist: pytest>=3.7; extra == "dev"
Dynamic: author
Dynamic: author-email
Dynamic: classifier
Dynamic: description
Dynamic: description-content-type
Dynamic: home-page
Dynamic: license-file
Dynamic: provides-extra
Dynamic: requires-dist
Dynamic: summary
